<annotated>
  <text>
    <p><w c7="II">during</w></p>
    <p><w c7="AT">the</w><w c7="MD">second</w><w c7="NN1">term</w><w c7="IO">of</w><w c7="NNB">President</w><w c7="NP1">Reagan</w><w c7="GE">'s</w></p>
    <p><w c7="NN1">administration</w><w c7="II">in</w><w c7="AT">the</w><w c7="NP121">United</w><w c7="NP122">States</w></p>
    <p><w c7="IO">of</w><w c7="NP1">America</w></p>
    <p><w c7="NP1">William</w><w c7="NP1">Bennett</w></p>
    <p><w c7="NP1">Reagan</w><w c7="GE">'s</w><w c7="NP1">Secretary</w><w c7="IO">of</w><w c7="NP1">State</w><w c7="IF">for</w><w c7="NP1">Education</w></p>
    <p><w c7="RR">publicly</w><w c7="VVD">complained</w></p>
    <p><w c7="CST">that</w><w c7="AT">the</w><w c7="NN">people</w><w c7="PNQS">who</w><w c7="RR">really</w><w c7="VVD">ruled</w><w c7="AT">the</w><w c7="NP121">United</w><w c7="NP122">States</w><w c7="VBDR">were</w><w c7="XX">not</w><w c7="AT">the</w><w c7="JJ">current</w><w c7="NN2">occupants</w><w c7="IO">of</w><w c7="AT">the</w><w c7="JJ">White</w><w c7="NP1">House</w></p>
    <p><w c7="CCB">but</w><w c7="NP2">Liberals</w></p>
    <p><w c7="CC">and</w><w c7="APPGE">their</w><w c7="NN2">cronies</w></p>
    <p><w c7="PNQS">who</w><w c7="RR">consistently</w><w c7="VVD">displayed</w><w c7="AT1">a</w><w c7="NN1">disdain</w></p>
    <p><w c7="IF">for</w><w c7="AT">the</w><w c7="JJ">Judeo-Christian</w><w c7="NN2">values</w><w c7="DD1">that</w><w c7="VHD">had</w><w c7="VVN">made</w><w c7="NP1">America</w><w c7="JJ">great</w></p>
    <p><w c7="AT">the</w><w c7="JJ">political</w><w c7="NN1">commentator</w></p>
    <p><w c7="NP1">Rick</w><w c7="NP1">Hertzberg</w></p>
    <p><w c7="AT">the</w><w c7="NN1">son</w><w c7="IO">of</w><w c7="AT1">an</w><w c7="JJ">unbelieving</w><w c7="JJ">Jewish</w><w c7="NN1">father</w><w c7="CC">and</w><w c7="AT1">a</w><w c7="JJ">Quaker</w><w c7="NN1">mother</w></p>
    <p><w c7="VVD">fired</w><w c7="RP">off</w></p>
    <p><w c7="DD1">this</w><w c7="NN1">reply</w></p>
    <p><w c7="II">in</w><w c7="AT">the</w><w c7="NP131">New</w><w c7="NP132">Yorker</w><w c7="NP133">Magazine</w></p>
    <p><w c7="II">as</w><w c7="AT1">a</w><w c7="NN1">Judeo-Christian</w><w c7="PNQS">who</w><w c7="VHZ">has</w><w c7="AT1">an</w><w c7="NN1">aversion</w><w c7="II">to</w><w c7="NN1">religion</w></p>
    <p><w c7="CC">and</w><w c7="PNQS">who</w><w c7="VBZ">'s</w><w c7="II">as</w></p>
    <p><w c7="AT1">a</w></p>
    <p><w c7="PNQS">who</w><w c7="PNQS">who</w><w c7="VBZ">'s</w><w c7="AT1">an</w><w c7="NN1">American</w><w c7="RG">as</w><w c7="JJ">good</w><w c7="II">as</w><w c7="CC">or</w><w c7="JJR">better</w><w c7="CSN">than</w><w c7="DD">any</w><w c7="JJ">mouse-haired</w></p>
    <p><w c7="JJ">Bible-touting</w></p>
    <p><w c7="JJ">apartheid-promoting</w><w c7="NN1">evangelist</w></p>
    <p><w c7="II">on</w><w c7="DD">any</w><w c7="NP1">UHF</w><w c7="NN1">television</w><w c7="NN1">station</w><w c7="PPY">you</w><w c7="VM">can</w><w c7="VVI">name</w></p>
    <p><w c7="PPIS1">I</w><w c7="VM">must</w><w c7="VVI">protest</w></p>
    <p><w c7="RRQ">where</w><w c7="VBDZ">was</w><w c7="PPH1">it</w><w c7="VVN">written</w></p>
    <p><w c7="CST">that</w><w c7="CS">if</w><w c7="PPY">you</w><w c7="VD0">do</w><w c7="XX">n't</w><w c7="VVI">like</w><w c7="NN1">religion</w></p>
    <p><w c7="PPY">you</w><w c7="VBR">are</w><w c7="RR">somehow</w><w c7="VVN">disqualified</w><w c7="II">from</w><w c7="VBG">being</w><w c7="AT1">a</w><w c7="JJ">legitimate</w><w c7="NN1">American</w></p>
    <p><w c7="DDQ">what</w><w c7="VBDZ">was</w><w c7="NP1">Mark</w><w c7="NP1">Twain</w></p>
    <p><w c7="AT1">a</w><w c7="NN1">Russian</w></p>
    <p><w c7="RRQ">when</w><w c7="VDD">did</w><w c7="PPH1">it</w><w c7="VVI">become</w></p>
    <p><w c7="JJ">un-American</w><w c7="TO">to</w><w c7="VHI">have</w><w c7="NN2">opinions</w></p>
    <p><w c7="II">about</w><w c7="AT">the</w><w c7="NN1">origin</w><w c7="CC">and</w><w c7="NN1">meaning</w><w c7="IO">of</w><w c7="AT">the</w><w c7="NN1">universe</w><w c7="DD1">that</w><w c7="VV0">come</w><w c7="II">from</w><w c7="NN2">sources</w></p>
    <p><w c7="II21">other</w><w c7="II22">than</w><w c7="AT">the</w><w c7="NN1">body</w><w c7="IO">of</w><w c7="NN1">dogma</w></p>
    <p><w c7="IO">of</w><w c7="NN2">organisations</w><w c7="VVN">approved</w><w c7="II">by</w><w c7="AT">the</w><w c7="JJ">federal</w><w c7="NN1">government</w></p>
    <p><w c7="II">as</w><w c7="RR">certifiably</w></p>
    <p><w c7="JJ">Judeo-Christian</w></p>
    <p><w c7="CS">if</w><w c7="PPH1">it</w><w c7="VBZ">'s</w><w c7="JJ">American</w><w c7="TO">to</w><w c7="VVI">believe</w></p>
    <p><w c7="CST">that</w><w c7="NN1">God</w><w c7="VVD">ordered</w><w c7="NN1">tribe</w><w c7="ZZ1">X</w><w c7="TO">to</w><w c7="VVI">abjure</w><w c7="NN1">pork</w></p>
    <p><w c7="CC">or</w><w c7="CST">that</w><w c7="PPHS1">he</w><w c7="VVD">caused</w></p>
    <p><w c7="NN1">leader</w><w c7="ZZ1">Y</w><w c7="TO">to</w><w c7="VBI">be</w><w c7="VVN">born</w><w c7="II">to</w><w c7="AT1">a</w><w c7="NN1">virgin</w></p>
    <p><w c7="RRQ">why</w><w c7="VBZ">is</w><w c7="PPH1">it</w><w c7="RR">suddenly</w><w c7="JJ">un-American</w><w c7="TO">to</w><w c7="VVI">doubt</w></p>
    <p><w c7="CST">that</w><w c7="AT">the</w><w c7="JJ">prime</w><w c7="NN1">mover</w><w c7="IO">of</w><w c7="DD1">this</w><w c7="RR">unimaginably</w><w c7="JJ">vast</w><w c7="NN1">universe</w></p>
    <p><w c7="IO">of</w><w c7="NNO2">quintillions</w></p>
    <p><w c7="IO">of</w><w c7="JJ">solar</w><w c7="NN2">systems</w></p>
    <p><w c7="VM">would</w><w c7="VBI">be</w><w c7="JJ">likely</w><w c7="TO">to</w><w c7="VBI">be</w><w c7="JJ">obsessed</w><w c7="IW">with</w><w c7="NN2">questions</w></p>
    <p><w c7="VVG">involving</w><w c7="AT">the</w><w c7="JJ">dietary</w></p>
    <p><w c7="CC">and</w><w c7="JJ">biosexual</w><w c7="NN1">behaviour</w></p>
    <p><w c7="IO">of</w><w c7="AT1">a</w><w c7="DA2">few</w><w c7="NNO">thousand</w><w c7="NN2">bipeds</w></p>
    <p><w c7="VVG">inhabiting</w><w c7="AT1">a</w><w c7="JJ">small</w><w c7="NN1">part</w></p>
    <p><w c7="IO">of</w><w c7="AT1">a</w><w c7="NN1">speck</w><w c7="IO">of</w><w c7="NN1">dust</w></p>
    <p><w c7="VVG">orbiting</w><w c7="AT1">a</w><w c7="JJ">third-rate</w><w c7="NN1">star</w></p>
    <p><w c7="II">in</w><w c7="AT1">an</w><w c7="JJ">obscure</w><w c7="JJ">spiral</w><w c7="NN1">arm</w></p>
    <p><w c7="IO">of</w><w c7="MC1">one</w><w c7="IO">of</w><w c7="AT1">a</w><w c7="NNO">million</w><w c7="NN2">galaxies</w></p>
    <p><w c7="NN1">end</w><w c7="IO">of</w><w c7="NN1">quote</w></p>
    <p><w c7="CC">and</w><w c7="DD1">that</w><w c7="VBZ">'s</w><w c7="AT1">a</w></p>
    <p><w c7="NN1">quote</w><w c7="IW">with</w><w c7="NN1">chuzpa</w></p>
    <p><w c7="PPIS1">I</w><w c7="VV0">want</w><w c7="TO">to</w><w c7="VVI">offer</w><w c7="MC">two</w></p>
    <p><w c7="NN2">words</w><w c7="II31">in</w><w c7="II32">response</w><w c7="II33">to</w><w c7="DD1">that</w><w c7="JJ">eloquent</w><w c7="NN1">outburst</w><w c7="CC">and</w><w c7="APPGE">my</w><w c7="MD">first</w><w c7="NN1">word</w><w c7="VBZ">is</w><w c7="UH">Amen</w></p>
    <p><w c7="UH">Amen</w><w c7="CS">because</w><w c7="II">like</w><w c7="NP1">Rick</w><w c7="NP1">Hertzberg</w></p>
    <p><w c7="PPIS1">I</w><w c7="VV0">object</w><w c7="II">to</w><w c7="AT">the</w><w c7="NN1">way</w></p>
    <p><w c7="DD">some</w><w c7="JJ">religious</w><w c7="NN2">leaders</w><w c7="VV0">rate</w><w c7="APPGE">their</w><w c7="JJ">sacred</w><w c7="NN1">text</w><w c7="II">above</w><w c7="DB">all</w><w c7="JJ">other</w><w c7="NN2">texts</w><w c7="II">on</w><w c7="NN1">earth</w></p>
    <p><w c7="II">as</w><w c7="NN2">carriers</w><w c7="IO">of</w><w c7="NN1">knowledge</w><w c7="CC">and</w><w c7="NN1">wisdom</w></p>
    <p><w c7="CS">so</w><w c7="PPIS1">I</w><w c7="VV0">say</w></p>
    <p><w c7="UH">Amen</w></p>
    <p><w c7="II">to</w><w c7="NP1">Rick</w><w c7="NP1">Hertzberg</w><w c7="GE">'s</w></p>
    <p><w c7="NN1">protest</w><w c7="II">at</w><w c7="JJ">religious</w><w c7="NN1">arrogance</w></p>
    <p><w c7="CC">and</w><w c7="APPGE">its</w><w c7="NN1">tendency</w><w c7="TO">to</w><w c7="VVI">think</w><w c7="APPGE">its</w><w c7="NN2">values</w></p>
    <p><w c7="VBR">are</w><w c7="AT">the</w><w c7="JJ">only</w><w c7="NN2">values</w><w c7="JJ">available</w><w c7="II">to</w><w c7="PPIO2">us</w></p>
    <p><w c7="CCB">but</w><w c7="APPGE">my</w><w c7="MD">second</w><w c7="NN1">word</w><w c7="VHZ">has</w><w c7="TO">to</w><w c7="VBI">be</w></p>
    <p><w c7="RR">nevertheless</w></p>
    <p><w c7="CS">because</w><w c7="PPH1">it</w><w c7="VBZ">is</w><w c7="II">by</w><w c7="NN">means</w></p>
    <p><w c7="IO">of</w><w c7="DD2">these</w><w c7="DA2">few</w><w c7="NNO">thousand</w><w c7="NN2">bipeds</w><w c7="VVN">called</w><w c7="NN121">homo</w><w c7="NN122">sapiens</w></p>
    <p><w c7="CST">that</w><w c7="DD1">this</w><w c7="NN1">universe</w></p>
    <p><w c7="VBZ">is</w><w c7="VVG">thinking</w><w c7="II">about</w><w c7="PPX1">itself</w></p>
    <p><w c7="CC">and</w><w c7="VHZ">has</w><w c7="VVN">become</w><w c7="JJ">aware</w><w c7="IO">of</w><w c7="APPGE">its</w><w c7="DA">own</w><w c7="NN1">existence</w></p>
    <p><w c7="EX">there</w><w c7="VM">may</w><w c7="VBI">be</w><w c7="JJ">self-conscious</w></p>
    <p><w c7="JJ">rational</w><w c7="NN2">creatures</w></p>
    <p><w c7="II">in</w><w c7="JJ">other</w><w c7="NN2">corners</w><w c7="IO">of</w><w c7="AT">the</w><w c7="NN1">universe</w></p>
    <p><w c7="CCB">but</w><w c7="PPIS2">we</w><w c7="VBR">are</w><w c7="AT">the</w><w c7="JJ">only</w><w c7="NN2">ones</w><w c7="PPIS2">we</w><w c7="VV0">know</w><w c7="II">about</w></p>
    <p><w c7="CC">and</w><w c7="PPH1">it</w><w c7="VVZ">seems</w><w c7="TO">to</w><w c7="VHI">have</w><w c7="VVN">taken</w></p>
    <p><w c7="AT">the</w><w c7="NN1">universe</w><w c7="MC">fourteen</w><w c7="NNO">billion</w><w c7="NNT2">years</w><w c7="IF">for</w><w c7="PPIO2">us</w><w c7="TO">to</w><w c7="VVI">appear</w></p>
    <p><w c7="UH">well</w><w c7="AT">the</w><w c7="NN1">universe</w><w c7="VM">may</w><w c7="XX">not</w><w c7="VBI">be</w><w c7="II">in</w><w c7="AT1">a</w><w c7="NN1">hurry</w><w c7="TO">to</w><w c7="VVI">explain</w></p>
    <p><w c7="CC">and</w><w c7="VVI">understand</w><w c7="PPX1">itself</w><w c7="CCB">but</w><w c7="PPIS2">we</w><w c7="VBR">are</w></p>
    <p><w c7="CS">since</w><w c7="PPIS2">we</w><w c7="VVD">arrived</w><w c7="II">on</w><w c7="AT">the</w><w c7="NN1">scene</w><w c7="RG">about</w><w c7="MC">fifty</w><w c7="NNO">thousand</w><w c7="NNT2">years</w><w c7="RA">ago</w></p>
    <p><w c7="RR">mentally</w><w c7="JJ">ready</w><w c7="CC">and</w><w c7="JJ">raring</w><w c7="TO">to</w><w c7="VVI">go</w></p>
    <p><w c7="APPGE">our</w><w c7="NN1">knowledge</w><w c7="IO">of</w><w c7="NN1">reality</w><w c7="VHZ">has</w><w c7="VVN">increased</w><w c7="RG">so</w><w c7="RR">rapidly</w></p>
    <p><w c7="CST">that</w><w c7="PPIS1">I</w><w c7="VBM">'m</w><w c7="VVN">tempted</w><w c7="TO">to</w><w c7="VVI">think</w><w c7="CST">that</w><w c7="II21">next</w><w c7="II22">to</w><w c7="NN1">light</w><w c7="PPX1">itself</w></p>
    <p><w c7="AT">the</w><w c7="JJ">human</w><w c7="NN1">mind</w></p>
    <p><w c7="VBZ">is</w><w c7="AT">the</w><w c7="JJT">fastest</w><w c7="NN1">thing</w><w c7="II">in</w><w c7="AT">the</w><w c7="NN1">universe</w></p>
    <p><w c7="RL">here</w><w c7="VBZ">'s</w><w c7="AT1">a</w><w c7="NN1">poem</w></p>
    <p><w c7="DD1">that</w><w c7="VVZ">captures</w><w c7="AT">the</w><w c7="NN1">wonder</w><w c7="IO">of</w><w c7="PPH1">it</w><w c7="DB">all</w></p>
    <p><w c7="II">by</w></p>
    <p><w c7="NP1">Primo</w><w c7="NP1">Levi</w></p>
    <p><w c7="AT1">a</w><w c7="NN1">survivor</w><w c7="IO">of</w><w c7="AT">the</w><w c7="NP1">Holocaust</w><w c7="AT1">a</w><w c7="NN1">chemist</w></p>
    <p><w c7="AT1">a</w><w c7="NN1">humanist</w></p>
    <p><w c7="AT1">a</w><w c7="NN1">poet</w></p>
    <p><w c7="PNQS">who</w><w c7="VVD">carried</w><w c7="AT">the</w><w c7="NN1">pain</w></p>
    <p><w c7="IO">of</w><w c7="AT">the</w><w c7="MD">twentieth</w><w c7="NNT1">century</w></p>
    <p><w c7="II">into</w><w c7="APPGE">his</w><w c7="DA">own</w><w c7="NN1">suicide</w></p>
    <p><w c7="JJ">fellow</w><w c7="NN2">humans</w></p>
    <p><w c7="II">to</w><w c7="PNQO">whom</w><w c7="AT1">a</w><w c7="NNT1">year</w><w c7="VBZ">is</w><w c7="AT1">a</w><w c7="JJ">long</w><w c7="NNT1">time</w></p>
    <p><w c7="AT1">a</w><w c7="NN1">sanctuary</w><w c7="AT1">a</w><w c7="JJ">venerable</w><w c7="NN1">goal</w></p>
    <p><w c7="VVG">struggling</w><w c7="IF">for</w><w c7="APPGE">your</w><w c7="NN1">bread</w></p>
    <p><w c7="JJ">tired</w></p>
    <p><w c7="JJ">threatful</w><w c7="JJ">tricked</w></p>
    <p><w c7="JJ">sick</w></p>
    <p><w c7="JJ">lost</w></p>
    <p><w c7="VV0">listen</w></p>
    <p><w c7="CC">and</w><w c7="VM">may</w><w c7="PPH1">it</w><w c7="VBI">be</w><w c7="NN1">mockery</w><w c7="CC">and</w></p>
    <p><w c7="NN1">consolation</w></p>
    <p><w c7="MC">twenty</w><w c7="NNO">billion</w><w c7="NNT2">years</w><w c7="II">before</w><w c7="RT">now</w></p>
    <p><w c7="JJ">brilliant</w></p>
    <p><w c7="VVG">soaring</w><w c7="II">in</w><w c7="NN1">space</w><w c7="CC">and</w><w c7="NNT1">time</w></p>
    <p><w c7="EX">there</w><w c7="VBDZ">was</w><w c7="AT1">a</w><w c7="NN1">ball</w><w c7="IO">of</w><w c7="NN1">flame</w></p>
    <p><w c7="JJ">solitary</w></p>
    <p><w c7="JJ">eternal</w></p>
    <p><w c7="APPGE">our</w><w c7="JJ">common</w><w c7="NN1">father</w></p>
    <p><w c7="CC">and</w><w c7="APPGE">our</w><w c7="NN1">executioner</w></p>
    <p><w c7="PPH1">it</w><w c7="VVD">exploded</w></p>
    <p><w c7="CC">and</w><w c7="AT1">every</w><w c7="NN1">change</w><w c7="VVD">began</w></p>
    <p><w c7="RR">even</w><w c7="RT">now</w><w c7="AT">the</w><w c7="JJ">thin</w><w c7="NN1">echo</w><w c7="IO">of</w><w c7="DD1">this</w><w c7="MC1">one</w><w c7="JJ">reverse</w><w c7="NN1">catastrophe</w></p>
    <p><w c7="VVZ">resounds</w><w c7="II">from</w><w c7="AT">the</w><w c7="NN1">father</w><w c7="GE">'s</w><w c7="NN2">reaches</w></p>
    <p><w c7="II">from</w><w c7="DD1">that</w><w c7="MC1">one</w><w c7="NN1">spasm</w><w c7="PN1">everything</w><w c7="VBDZ">was</w><w c7="VVN">born</w></p>
    <p><w c7="AT">the</w><w c7="DA">same</w><w c7="NN1">abyss</w><w c7="DD1">that</w><w c7="VVZ">enfolds</w><w c7="CC">and</w><w c7="VVZ">challenges</w><w c7="PPIO2">us</w></p>
    <p><w c7="AT">the</w><w c7="DA">same</w><w c7="NNT1">time</w><w c7="DD1">that</w><w c7="NN2">spawns</w><w c7="CC">and</w><w c7="NN2">defeats</w><w c7="PPIO2">us</w></p>
    <p><w c7="PN1">everything</w></p>
    <p><w c7="PN1">anyone</w><w c7="VHZ">has</w><w c7="RR">ever</w><w c7="VVN">thought</w></p>
    <p><w c7="AT">the</w><w c7="NN2">eyes</w><w c7="IO">of</w><w c7="AT1">every</w><w c7="NN1">woman</w><w c7="PPIS2">we</w><w c7="VH0">have</w><w c7="VVN">loved</w></p>
    <p><w c7="NN2">suns</w><w c7="II">by</w><w c7="AT">the</w><w c7="NNO2">thousands</w></p>
    <p><w c7="CC">and</w><w c7="DD1">this</w><w c7="NN1">hand</w></p>
    <p><w c7="DD1">that</w><w c7="VVZ">writes</w></p>
    <p><w c7="CC">and</w><w c7="DD1">this</w><w c7="NN1">hand</w></p>
    <p><w c7="DD1">that</w><w c7="VVZ">writes</w></p>
    <p><w c7="DD1">that</w><w c7="VBZ">'s</w><w c7="DDQ">what</w><w c7="PPIS1">I</w><w c7="VV0">want</w><w c7="TO">to</w><w c7="VVI">think</w><w c7="II">about</w><w c7="DD1">this</w><w c7="NNT1">evening</w></p>
    <p><w c7="AT">the</w><w c7="JJ">astonishing</w><w c7="NN1">creativity</w></p>
    <p><w c7="IO">of</w><w c7="AT">the</w><w c7="JJ">human</w><w c7="NN1">animal</w></p>
    <p><w c7="VVG">flowing</w><w c7="II">from</w><w c7="AT">the</w><w c7="JJ">big</w><w c7="NN2">brains</w></p>
    <p><w c7="DD1">that</w><w c7="VH0">have</w><w c7="VVN">evolved</w><w c7="II">in</w><w c7="PPIO2">us</w><w c7="TO">to</w><w c7="VBI">be</w><w c7="NN2">instruments</w></p>
    <p><w c7="IO">of</w><w c7="NN1">communication</w></p>
    <p><w c7="CC">and</w><w c7="NN1">transformation</w></p>
    <p><w c7="PPH1">it</w><w c7="VBZ">is</w><w c7="II">from</w><w c7="APPGE">our</w><w c7="NN2">minds</w></p>
    <p><w c7="CC">and</w><w c7="APPGE">their</w><w c7="NN1">desire</w><w c7="TO">to</w><w c7="VVI">understand</w><w c7="NN1">existence</w></p>
    <p><w c7="CST">that</w><w c7="NN1">religion</w></p>
    <p><w c7="CC">and</w><w c7="NN1">science</w></p>
    <p><w c7="CC">and</w></p>
    <p><w c7="NN1">philosophy</w><w c7="VH0">have</w><w c7="VVN">emerged</w></p>
    <p><w c7="CCB">but</w><w c7="DD1">this</w><w c7="NNT1">evening</w></p>
    <p><w c7="PPIS1">I</w><w c7="VV0">want</w><w c7="TO">to</w><w c7="VVI">concentrate</w><w c7="II">on</w><w c7="DD1">another</w><w c7="NN1">aspect</w><w c7="IO">of</w><w c7="APPGE">our</w><w c7="JJ">fertile</w><w c7="NN2">minds</w></p>
    <p><w c7="JJ">human</w><w c7="NN1">art</w></p>
    <p><w c7="CC">and</w><w c7="NN1">culture</w></p>
    <p><w c7="NN1">culture</w><w c7="VHZ">has</w><w c7="VBN">been</w><w c7="VVN">defined</w><w c7="II">as</w><w c7="DD">any</w></p>
    <p><w c7="JJ">widespread</w><w c7="NN1">behaviour</w></p>
    <p><w c7="DD1">that</w><w c7="VBZ">is</w><w c7="VVN">transmitted</w><w c7="II">by</w><w c7="NN1">learning</w></p>
    <p><w c7="CS21">rather</w><w c7="CS22">than</w><w c7="VVN">acquired</w><w c7="II">by</w><w c7="NN1">inheritance</w></p>
    <p><w c7="CC">and</w><w c7="II">on</w><w c7="DD1">this</w><w c7="NN1">planet</w><w c7="PPH1">it</w><w c7="VBZ">is</w><w c7="JJ">unique</w><w c7="II">to</w><w c7="PPIO2">us</w></p>
    <p><w c7="PPIS2">we</w><w c7="VBR">are</w><w c7="AT">the</w><w c7="JJ">creative</w><w c7="NN1">animal</w></p>
    <p><w c7="PPY">you</w><w c7="VM">wo</w><w c7="XX">n't</w><w c7="VVI">find</w></p>
    <p><w c7="AT1">a</w><w c7="NN1">bunch</w><w c7="IO">of</w><w c7="JJ">other</w><w c7="NN2">animals</w></p>
    <p><w c7="VVN">dedicated</w><w c7="II">to</w><w c7="VVG">listening</w><w c7="II">to</w><w c7="AT1">a</w><w c7="JJ">boring</w><w c7="NN1">lecture</w><w c7="RL">anywhere</w><w c7="RR">else</w><w c7="II">on</w><w c7="AT">the</w><w c7="NN1">planet</w><w c7="DD1">this</w><w c7="NNT1">evening</w></p>
    <p><w c7="AT">no</w></p>
    <p><w c7="NN2">colloquies</w><w c7="IO">of</w><w c7="NN2">camels</w><w c7="VVG">meeting</w><w c7="TO">to</w><w c7="VVI">discuss</w><w c7="AT">the</w><w c7="NN1">nature</w><w c7="IO">of</w><w c7="NN1">camelhood</w></p>
    <p><w c7="CCB">but</w><w c7="RL">here</w><w c7="PPIS2">we</w><w c7="VBR">are</w></p>
    <p><w c7="CC">and</w><w c7="PPIS2">we</w><w c7="VD0">do</w><w c7="PPH1">it</w><w c7="DB">all</w><w c7="AT">the</w><w c7="NNT1">time</w><w c7="CS">because</w><w c7="PPIS2">we</w><w c7="VBR">are</w><w c7="AT">the</w></p>
    <p><w c7="JJ">creative</w><w c7="NN1">animal</w><w c7="AT">the</w><w c7="JJ">thinking</w><w c7="NN1">animal</w></p>
    <p><w c7="AT">the</w><w c7="NN1">animal</w><w c7="DD1">that</w><w c7="VBZ">'s</w><w c7="AT1">an</w><w c7="NN1">object</w><w c7="IO">of</w><w c7="NN1">interest</w><w c7="II">to</w><w c7="PPX1">itself</w></p>
    <p><w c7="CC">and</w></p>
    <p><w c7="AT">the</w><w c7="NN1">universe</w></p>
    <p><w c7="VBZ">is</w><w c7="AT1">an</w><w c7="NN1">object</w><w c7="IO">of</w><w c7="NN1">interest</w><w c7="II">to</w><w c7="PPX1">itself</w></p>
    <p><w c7="II">at</w><w c7="AT">the</w><w c7="NN1">root</w></p>
    <p><w c7="IO">of</w><w c7="APPGE">our</w><w c7="NN1">ability</w></p>
    <p><w c7="TO">to</w><w c7="VVI">create</w><w c7="NN1">culture</w></p>
    <p><w c7="PPIS1">I</w><w c7="VV0">believe</w></p>
    <p><w c7="VBZ">is</w><w c7="AT">the</w><w c7="NN1">problem</w><w c7="PPIS2">we</w><w c7="VH0">have</w><w c7="IW">with</w><w c7="NNT1">time</w></p>
    <p><w c7="CC">and</w><w c7="APPGE">its</w><w c7="NN1">companion</w></p>
    <p><w c7="NN1">boredom</w></p>
    <p><w c7="RR">just</w><w c7="VV0">think</w><w c7="IO">of</w><w c7="AT1">a</w><w c7="DA2">few</w><w c7="IO">of</w><w c7="AT">the</w><w c7="NN2">ways</w><w c7="PPIS2">we</w><w c7="VV0">talk</w></p>
    <p><w c7="II">about</w><w c7="NNT1">time</w></p>
    <p><w c7="VVG">passing</w><w c7="NNT1">time</w></p>
    <p><w c7="VVG">filling</w><w c7="NNT1">time</w></p>
    <p><w c7="VVG">redeeming</w><w c7="NNT1">time</w></p>
    <p><w c7="VDG">doing</w></p>
    <p><w c7="NNT1">time</w></p>
    <p><w c7="CC">and</w><w c7="PPY">you</w><w c7="VD0">do</w><w c7="XX">n't</w></p>
    <p><w c7="RR">just</w><w c7="VH0">have</w><w c7="TO">to</w><w c7="VBI">be</w><w c7="AT1">a</w><w c7="NN1">prisoner</w><w c7="TO">to</w><w c7="VVI">understand</w><w c7="AT">the</w><w c7="NN1">boredom</w><w c7="IO">of</w><w c7="DD1">that</w></p>
    <p><w c7="NN1">kind</w><w c7="IO">of</w><w c7="NN1">stretch</w><w c7="IO">of</w><w c7="NNT1">time</w></p>
    <p><w c7="PPH1">it</w><w c7="VVZ">seems</w></p>
    <p><w c7="II">to</w><w c7="PPIO2">us</w></p>
    <p><w c7="AT">the</w><w c7="JJ">creative</w><w c7="NN1">animal</w></p>
    <p><w c7="CST">that</w><w c7="RR">once</w><w c7="AT">the</w><w c7="NN2">necessities</w><w c7="IO">of</w><w c7="NN1">life</w><w c7="VBR">are</w><w c7="RGR">more</w><w c7="CC">or</w><w c7="RGR">less</w><w c7="JJ">povided</w><w c7="IF">for</w></p>
    <p><w c7="AT">the</w><w c7="JJ">human</w></p>
    <p><w c7="NN1">animal</w><w c7="VHZ">has</w><w c7="AT1">a</w><w c7="NN1">problem</w><w c7="IW">with</w><w c7="NNT1">time</w><w c7="CC">and</w><w c7="DDQ">what</w><w c7="TO">to</w><w c7="VDI">do</w><w c7="IW">with</w><w c7="PPH1">it</w></p>
    <p><w c7="CC">and</w><w c7="DDQ">what</w><w c7="PPIS2">we</w><w c7="VH0">'ve</w><w c7="VDN">done</w><w c7="IW">with</w><w c7="PPH1">it</w></p>
    <p><w c7="VBZ">is</w><w c7="TO">to</w><w c7="VVI">fill</w><w c7="PPH1">it</w><w c7="IW">with</w><w c7="JJ">imaginative</w><w c7="NN2">inventions</w></p>
    <p><w c7="DD1">that</w><w c7="VV0">become</w><w c7="RGR">more</w><w c7="CC">and</w><w c7="RGR">more</w><w c7="JJ">complex</w><w c7="CC">and</w><w c7="JJ">absorbing</w></p>
    <p><w c7="CC">and</w><w c7="RT">sometimes</w><w c7="PPHS2">they</w><w c7="VBR">are</w><w c7="RR">astonishingly</w><w c7="JJ">beautiful</w></p>
    <p><w c7="DD1">this</w><w c7="VBZ">is</w><w c7="AT">the</w><w c7="NN1">impulse</w></p>
    <p><w c7="DD1">that</w><w c7="VVZ">gives</w><w c7="PPIO2">us</w><w c7="PN1">everything</w><w c7="II">from</w><w c7="NP1">Sudoku</w></p>
    <p><w c7="II">to</w><w c7="NN2">symphonies</w></p>
    <p><w c7="JJ">literary</w><w c7="NN2">masterpieces</w></p>
    <p><w c7="CC">and</w><w c7="NN1">television</w><w c7="NN1">soap</w><w c7="NN2">operas</w></p>
    <p><w c7="CC">and</w><w c7="RR">even</w><w c7="DD1">that</w><w c7="JJ">strange</w><w c7="JJ">Scottish</w><w c7="NN1">pastime</w></p>
    <p><w c7="VVG">hitting</w><w c7="AT1">a</w><w c7="JJ">wee</w><w c7="JJ">white</w><w c7="NN1">ball</w><w c7="II">into</w><w c7="AT">the</w><w c7="NN1">face</w><w c7="IO">of</w><w c7="AT1">a</w><w c7="NN1">force</w><w c7="MC">ten</w><w c7="NN1">gale</w></p>
    <p><w c7="CC">and</w><w c7="VVG">claiming</w><w c7="TO">to</w><w c7="VVI">enjoy</w><w c7="PPH1">it</w></p>
    <p><w c7="NN1">golf</w></p>
    <p><w c7="PPIS2">we</w><w c7="VD0">do</w><w c7="DD2">these</w><w c7="NN2">things</w><w c7="VV0">watch</w><w c7="NN">people</w><w c7="II">on</w><w c7="AT1">a</w><w c7="NN1">train</w><w c7="PPY">you</w><w c7="VH0">'ve</w><w c7="VVN">got</w><w c7="MC">five</w><w c7="NNT2">hours</w><w c7="TO">to</w><w c7="VVI">go</w><w c7="II">from</w></p>
    <p><w c7="NP1">Waverley</w><w c7="II">to</w><w c7="NP1">King</w><w c7="GE">'s</w><w c7="NP1">Cross</w></p>
    <p><w c7="NN">people</w><w c7="VBR">are</w><w c7="VVG">reading</w></p>
    <p><w c7="PPHS2">they</w><w c7="VBR">'re</w><w c7="VDG">doing</w><w c7="NN2">crosswords</w></p>
    <p><w c7="PPHS2">they</w><w c7="VBR">'re</w><w c7="VDG">doing</w><w c7="APPGE">their</w><w c7="NN2">emails</w><w c7="PPHS2">they</w><w c7="VBR">'re</w><w c7="VVG">shouting</w><w c7="II">into</w><w c7="APPGE">their</w><w c7="NN2">phones</w></p>
    <p><w c7="AT">the</w><w c7="MC1">one</w><w c7="NN1">thing</w><w c7="PPHS2">they</w><w c7="VD0">do</w><w c7="XX">n't</w><w c7="VDI">do</w><w c7="VBZ">is</w><w c7="PN1">nothing</w></p>
    <p><w c7="CS">because</w><w c7="NNT1">time</w></p>
    <p><w c7="VHZ">has</w><w c7="TO">to</w><w c7="VBI">be</w><w c7="VVN">filled</w></p>
    <p><w c7="NNT1">time</w><w c7="VVZ">stretches</w><w c7="PPH1">it</w><w c7="VVZ">troubles</w><w c7="PPIO2">us</w></p>
    <p><w c7="CS">if</w><w c7="PPIS2">we</w><w c7="VBR">'re</w></p>
    <p><w c7="II">on</w><w c7="APPGE">our</w><w c7="DA">own</w><w c7="IW">with</w><w c7="PN1">nothing</w><w c7="TO">to</w><w c7="VDI">do</w></p>
    <p><w c7="CS">if</w><w c7="VVG">trying</w><w c7="TO">to</w><w c7="VVI">distract</w><w c7="PPX2">ourselves</w></p>
    <p><w c7="II">from</w><w c7="AT">the</w><w c7="NN1">boredom</w></p>
    <p><w c7="IO">of</w><w c7="VVG">plodding</w><w c7="NNT1">time</w></p>
    <p><w c7="VBZ">is</w><w c7="MC1">one</w><w c7="IO">of</w><w c7="AT">the</w><w c7="NN2">roots</w><w c7="IO">of</w><w c7="NN1">art</w></p>
    <p><w c7="RT">then</w><w c7="DD1">another</w><w c7="VBZ">is</w><w c7="RR">even</w><w c7="RGR">more</w><w c7="JJ">surprising</w></p>
    <p><w c7="NN1">art</w><w c7="VBZ">is</w><w c7="MC1">one</w><w c7="IO">of</w><w c7="AT">the</w><w c7="NN2">ways</w><w c7="II">in</w><w c7="DDQ">which</w><w c7="AT">the</w><w c7="NN">troubled</w><w c7="CC">or</w><w c7="NN">despised</w></p>
    <p><w c7="VH0">have</w><w c7="VVN">sought</w><w c7="TO">to</w><w c7="VVI">console</w></p>
    <p><w c7="CC">and</w><w c7="VVI">understand</w><w c7="PPX2">themselves</w></p>
    <p><w c7="AT">the</w><w c7="NN1">novelist</w><w c7="NP1">Rebecca</w><w c7="NP1">West</w><w c7="VVD">claimed</w></p>
    <p><w c7="CST">that</w><w c7="JJ">artistic</w><w c7="NN1">genius</w></p>
    <p><w c7="VBDZ">was</w></p>
    <p><w c7="CC">and</w><w c7="DD1">this</w><w c7="NN1">phrase</w><w c7="VBZ">is</w><w c7="II">in</w><w c7="NN2">quotes</w><w c7="AT">the</w><w c7="NN1">abnormal</w><w c7="VVG">justifying</w><w c7="PPX1">itself</w></p>
    <p><w c7="NN1">end</w><w c7="IO">of</w><w c7="NN1">quote</w></p>
    <p><w c7="CC">and</w><w c7="PPHS1">she</w><w c7="VVD">went</w><w c7="RP">on</w></p>
    <p><w c7="DD2">those</w><w c7="PNQS">who</w><w c7="VV0">know</w></p>
    <p><w c7="CST">that</w><w c7="PPHS2">they</w><w c7="VBR">are</w><w c7="IF">for</w><w c7="DDQV">whatever</w><w c7="NN1">reason</w><w c7="VVN">condemned</w><w c7="II">by</w><w c7="AT">the</w><w c7="NN2">laws</w><w c7="IO">of</w><w c7="NN1">life</w></p>
    <p><w c7="VV0">make</w><w c7="PPX2">themselves</w><w c7="PN1">one</w><w c7="IW">with</w><w c7="NN1">life</w><w c7="II">by</w><w c7="DD">some</w></p>
    <p><w c7="JJ">magnificent</w><w c7="NN1">act</w><w c7="IO">of</w><w c7="NN1">creation</w></p>
    <p><w c7="PPIS1">I</w><w c7="VVD">found</w><w c7="DD2">those</w></p>
    <p><w c7="NN2">words</w><w c7="II">from</w></p>
    <p><w c7="NP1">Rebecca</w><w c7="NP1">West</w></p>
    <p><w c7="II">in</w><w c7="NP1">Victoria</w><w c7="NP1">Glenndinning</w><w c7="GE">'s</w></p>
    <p><w c7="JJ">wonderful</w><w c7="NN1">biography</w><w c7="IO">of</w><w c7="NP1">Vita</w></p>
    <p><w c7="NP121">Sackville</w></p>
	<p><w c7="NP122">-West</w></p>
    <p><w c7="AT">the</w><w c7="NN1">wife</w><w c7="IO">of</w><w c7="NP1">Harold</w><w c7="NP1">Nicolson</w></p>
    <p><w c7="NP1">Glenndinning</w><w c7="VVD">applied</w><w c7="PPHO2">them</w><w c7="II">to</w><w c7="NP1">Vita</w><w c7="PPX1">herself</w></p>
    <p><w c7="CC">and</w><w c7="VVD">suggested</w></p>
    <p><w c7="CST">that</w><w c7="APPGE">her</w><w c7="JJ">magnificent</w><w c7="NN1">act</w><w c7="IO">of</w><w c7="NN1">creation</w></p>
    <p><w c7="VBDZ">was</w><w c7="RR">neither</w><w c7="APPGE">her</w><w c7="NN1">poetry</w><w c7="CC">nor</w><w c7="APPGE">her</w><w c7="NN1">fiction</w></p>
    <p><w c7="CCB">but</w><w c7="AT">the</w><w c7="NN1">garden</w><w c7="DD1">that</w><w c7="PPHS1">she</w><w c7="VVD">created</w><w c7="II">at</w><w c7="NP1">Sissinghurst</w></p>
    <p><w c7="NP1">Castle</w><w c7="II">in</w><w c7="NP1">Kent</w></p>
    <p><w c7="CS">if</w><w c7="PPY">you</w><w c7="VH0">'ve</w><w c7="RR">ever</w><w c7="VBN">been</w><w c7="II">to</w><w c7="DD1">that</w><w c7="NN1">garden</w><w c7="PPY">you</w><w c7="VM">'ll</w><w c7="VVI">remember</w><w c7="DDQ">what</w><w c7="AT1">a</w><w c7="NN1">wonder</w><w c7="PPH1">it</w><w c7="VBZ">is</w><w c7="DD1">this</w><w c7="VBZ">is</w><w c7="RRQ">how</w><w c7="APPGE">her</w><w c7="NN1">son</w></p>
    <p><w c7="NP1">Nigel</w><w c7="VVZ">describes</w><w c7="PPH1">it</w></p>
    <p><w c7="NP1">Harold</w></p>
    <p><w c7="VVD">made</w><w c7="AT">the</w><w c7="NN1">design</w></p>
    <p><w c7="NP1">Vita</w></p>
    <p><w c7="VDD">did</w><w c7="AT">the</w><w c7="NN1">planting</w></p>
    <p><w c7="II">in</w><w c7="AT">the</w><w c7="JJ">firm</w><w c7="NN1">perspective</w><w c7="IO">of</w><w c7="NP1">Vista</w><w c7="GE">'s</w></p>
    <p><w c7="PN1">one</w><w c7="VM">can</w><w c7="VVI">trace</w><w c7="APPGE">his</w><w c7="JJ">classical</w><w c7="NN1">hand</w></p>
    <p><w c7="II">in</w><w c7="AT">the</w><w c7="JJ">overflowing</w><w c7="NN">clematis</w></p>
    <p><w c7="NN2">figs</w><w c7="NN2">vines</w><w c7="CC">and</w><w c7="NN1">wisteria</w></p>
    <p><w c7="II">in</w><w c7="AT">the</w><w c7="NN1">rejection</w><w c7="IO">of</w><w c7="JJ">violent</w><w c7="NN1">colour</w></p>
    <p><w c7="CC">or</w><w c7="PN1">anything</w><w c7="RG">too</w><w c7="JJ">tame</w><w c7="CC">or</w><w c7="JJ">orderly</w></p>
    <p><w c7="PN1">one</w><w c7="VVZ">discovers</w><w c7="PPHO1">her</w></p>
    <p><w c7="NN1">romanticism</w></p>
    <p><w c7="JJ">wild</w><w c7="NN2">flowers</w><w c7="VM">must</w><w c7="VBI">be</w><w c7="VVN">allowed</w><w c7="TO">to</w><w c7="VVI">invade</w><w c7="AT">the</w><w c7="NN1">garden</w></p>
    <p><w c7="CS">if</w><w c7="NN2">plants</w><w c7="VV0">stray</w><w c7="II">over</w><w c7="AT1">a</w><w c7="NN1">path</w></p>
    <p><w c7="PPHS2">they</w><w c7="VM">must</w><w c7="XX">not</w><w c7="VBI">be</w><w c7="VVN">cut</w><w c7="RP">back</w></p>
    <p><w c7="AT">the</w><w c7="NN1">visitor</w><w c7="VM">must</w><w c7="VVI">duck</w></p>
    <p><w c7="NN2">rhododendrons</w><w c7="VM">must</w><w c7="VBI">be</w><w c7="VVN">banished</w><w c7="II31">in</w><w c7="II32">favour</w><w c7="II33">of</w><w c7="APPGE">their</w><w c7="JJ">tender</w><w c7="NN1">cousin</w></p>
    <p><w c7="AT">the</w><w c7="NN">azalea</w></p>
    <p><w c7="NN2">roses</w><w c7="VM">must</w><w c7="XX">not</w><w c7="VVI">electrify</w></p>
    <p><w c7="CCB">but</w><w c7="VVI">seduce</w></p>
    <p><w c7="CC">and</w><w c7="CS">when</w><w c7="AT1">a</w><w c7="NNT1">season</w><w c7="VHZ">has</w><w c7="VVN">produced</w><w c7="APPGE">its</w><w c7="NN1">best</w></p>
    <p><w c7="DD1">that</w><w c7="NN1">part</w><w c7="IO">of</w><w c7="AT">the</w><w c7="NN1">garden</w><w c7="VM">must</w><w c7="VBI">be</w><w c7="VVN">allowed</w><w c7="TO">to</w><w c7="VVI">lie</w><w c7="JJ">fallow</w></p>
    <p><w c7="IF">for</w><w c7="DD1">another</w><w c7="NNT1">year</w></p>
    <p><w c7="CS">since</w><w c7="EX">there</w><w c7="VBZ">is</w><w c7="AT1">a</w><w c7="NN1">cycle</w><w c7="II">in</w><w c7="NN1">nature</w><w c7="DD1">that</w><w c7="VM">must</w><w c7="XX">not</w><w c7="VBI">be</w><w c7="VVN">disguised</w></p>
    <p><w c7="PPH1">it</w><w c7="VBZ">is</w><w c7="RR">eternally</w><w c7="JJ">renewable</w></p>
    <p><w c7="II">like</w><w c7="AT1">a</w><w c7="NN1">play</w></p>
    <p><w c7="IW">with</w><w c7="NN2">acts</w><w c7="CC">and</w><w c7="NN2">scenes</w></p>
    <p><w c7="EX">there</w><w c7="VM">can</w><w c7="VBI">be</w><w c7="AT1">a</w><w c7="NN1">change</w><w c7="IO">of</w><w c7="NN1">cast</w></p>
    <p><w c7="CCB">but</w><w c7="AT">the</w><w c7="NN1">script</w></p>
    <p><w c7="VVZ">remains</w><w c7="AT">the</w><w c7="DA">same</w></p>
    <p><w c7="NN1">permanence</w></p>
    <p><w c7="CC">and</w><w c7="NN1">mutation</w></p>
    <p><w c7="VBR">are</w><w c7="AT">the</w><w c7="NN2">secrets</w></p>
    <p><w c7="IO">of</w><w c7="DD1">this</w><w c7="NN1">garden</w></p>
    <p><w c7="CS">when</w><w c7="NP1">West</w></p>
    <p><w c7="VVD">described</w><w c7="NN2">artists</w></p>
    <p><w c7="II">as</w><w c7="VBG">being</w><w c7="VVN">condemned</w><w c7="II">by</w></p>
    <p><w c7="AT">the</w><w c7="NN2">laws</w><w c7="IO">of</w><w c7="NN1">life</w></p>
    <p><w c7="PPHS1">she</w><w c7="VBDZ">was</w><w c7="XX">not</w><w c7="RR21">of</w><w c7="RR22">course</w><w c7="VVG">talking</w></p>
    <p><w c7="II">about</w><w c7="AT">the</w><w c7="NN2">ways</w><w c7="IO">of</w><w c7="NN1">nature</w><w c7="RG">so</w><w c7="RR">lovingly</w><w c7="VVN">celebrated</w><w c7="II">by</w><w c7="NP1">Vita</w></p>
    <p><w c7="II">in</w><w c7="APPGE">her</w><w c7="NN1">garden</w></p>
    <p><w c7="CCB">but</w><w c7="IO">of</w><w c7="DD2">those</w><w c7="JJ">man-made</w><w c7="NN2">laws</w><w c7="PPIS2">we</w><w c7="VV0">call</w></p>
    <p><w c7="NN1">custom</w></p>
    <p><w c7="CC">or</w><w c7="NN1">morality</w></p>
    <p><w c7="NP1">Glendinning</w></p>
    <p><w c7="VVD">applied</w><w c7="DD1">this</w><w c7="NN1">insight</w><w c7="II">to</w><w c7="NP1">Vita</w><w c7="GE">'s</w><w c7="NN1">homosexuality</w></p>
    <p><w c7="CS">if</w><w c7="PPY">you</w><w c7="VBR">are</w><w c7="VVN">told</w><w c7="II">by</w><w c7="NN1">church</w><w c7="CC">and</w><w c7="NN1">society</w></p>
    <p><w c7="CST">that</w><w c7="DDQ">what</w><w c7="PPY">you</w><w c7="VBR">are</w><w c7="II">in</w><w c7="APPGE">your</w><w c7="JJ">very</w><w c7="NN1">essence</w><w c7="VBZ">is</w><w c7="JJ">wrong</w></p>
    <p><w c7="PPH1">it</w><w c7="VM">will</w><w c7="VVI">create</w></p>
    <p><w c7="AT1">a</w><w c7="NN1">dissonance</w></p>
    <p><w c7="AT1">a</w><w c7="NN1">disjunction</w></p>
    <p><w c7="II">between</w><w c7="APPGE">your</w><w c7="DA">own</w><w c7="NN1">soul</w></p>
    <p><w c7="CC">and</w><w c7="AT">the</w><w c7="NN2">norms</w><w c7="IO">of</w><w c7="AT">the</w><w c7="NN1">community</w></p>
    <p><w c7="DD1">that</w><w c7="VVZ">surrounds</w><w c7="PPY">you</w></p>
    <p><w c7="NP1">Rebecca</w><w c7="NP1">West</w><w c7="VBZ">is</w><w c7="VVG">saying</w></p>
    <p><w c7="CST">that</w><w c7="NN1">creativity</w></p>
    <p><w c7="VHZ">has</w><w c7="MC1">one</w><w c7="IO">of</w><w c7="APPGE">its</w><w c7="NN2">roots</w></p>
    <p><w c7="II">in</w><w c7="DD1">that</w></p>
    <p><w c7="NN1">disconnection</w></p>
    <p><w c7="II">between</w><w c7="JJ">prevailing</w><w c7="NN2">attitudes</w><w c7="CC">and</w><w c7="AT">the</w><w c7="NN1">reality</w></p>
    <p><w c7="IO">of</w><w c7="AT">the</w><w c7="NN1">maker</w><w c7="GE">'s</w><w c7="NN1">life</w></p>
    <p><w c7="DD1">that</w><w c7="NN1">dissonance</w><w c7="PPHS1">she</w><w c7="VVZ">suggests</w></p>
    <p><w c7="VBZ">is</w><w c7="AT">the</w><w c7="NN1">grit</w><w c7="II">in</w><w c7="AT">the</w><w c7="NN1">soul</w></p>
    <p><w c7="DD1">that</w><w c7="VVZ">becomes</w></p>
    <p><w c7="AT">the</w><w c7="NN1">pearl</w><w c7="IO">of</w><w c7="JJ">great</w><w c7="NN1">price</w></p>
    <p><w c7="JJ">wonderful</w><w c7="NN1">art</w></p>
    <p><w c7="RR21">of</w><w c7="RR22">course</w><w c7="AT">the</w><w c7="NN1">flipside</w><w c7="IO">of</w><w c7="DD1">that</w><w c7="NN1">process</w><w c7="VBZ">is</w><w c7="VVN">revealed</w></p>
    <p><w c7="CS">when</w><w c7="JJ">social</w><w c7="NN1">change</w><w c7="VVZ">swaps</w><w c7="NN1">curse</w><w c7="IF">for</w><w c7="NN1">blessing</w></p>
    <p><w c7="CC">and</w><w c7="AT">the</w><w c7="NN1">outlaw</w></p>
    <p><w c7="VBZ">is</w><w c7="VVN">brought</w><w c7="RP">in</w><w c7="II">from</w><w c7="AT">the</w><w c7="NN1">cold</w></p>
    <p><w c7="AT1">a</w><w c7="JJ">good</w><w c7="NN1">example</w><w c7="IO">of</w><w c7="DD1">this</w></p>
    <p><w c7="JJ">reverse</w><w c7="NN1">dynamic</w><w c7="VBZ">is</w><w c7="VVN">provided</w><w c7="II">by</w><w c7="AT">the</w><w c7="NN1">career</w></p>
    <p><w c7="IO">of</w><w c7="AT">the</w><w c7="NN1">playwright</w><w c7="NP1">Terence</w><w c7="NP1">Rattigan</w></p>
    <p><w c7="PNQS">who</w><w c7="VHZ">'s</w><w c7="VBN">been</w><w c7="VHG">having</w><w c7="AT1">a</w><w c7="NN1">bit</w><w c7="IO">of</w><w c7="AT1">a</w></p>
    <p><w c7="AT1">a</w><w c7="NN1">revival</w><w c7="RR">recently</w></p>
    <p><w c7="II">in</w><w c7="AT">the</w><w c7="NP1">West</w><w c7="NP1">End</w><w c7="II">in</w><w c7="NP1">London</w></p>
    <p><w c7="NP1">Rattigan</w><w c7="GE">'s</w><w c7="NN1">biographer</w><w c7="NP1">Michael</w><w c7="NP1">Darlow</w><w c7="VVD">pinpointed</w><w c7="AT">the</w><w c7="NN1">problem</w></p>
    <p><w c7="DD1">that</w><w c7="VVD">started</w><w c7="TO">to</w><w c7="VVI">confront</w><w c7="DB">all</w><w c7="JJ">homosexual</w><w c7="NN2">writers</w><w c7="II">in</w><w c7="NP1">Britain</w></p>
    <p><w c7="CS">when</w><w c7="AT">the</w><w c7="NN1">theatre</w><w c7="VVD">began</w><w c7="TO">to</w><w c7="VVI">change</w><w c7="II">in</w><w c7="AT">the</w><w c7="MC">nineteen</w><w c7="MC2">sixties</w></p>
    <p><w c7="DD1">this</w><w c7="VBZ">is</w><w c7="DDQ">what</w><w c7="PPHS1">he</w><w c7="VVD">wrote</w></p>
    <p><w c7="CS">until</w><w c7="AT">the</w><w c7="JJ">late</w><w c7="MC">nineteen</w><w c7="MC2">fifties</w></p>
    <p><w c7="NP1">Rattigan</w><w c7="GE">'s</w><w c7="NN1">art</w></p>
    <p><w c7="II">as</w><w c7="AT1">a</w><w c7="NN1">dramatist</w><w c7="VVD">depended</w><w c7="II">upon</w><w c7="AT">the</w><w c7="NN1">oblique</w></p>
    <p><w c7="AT">the</w><w c7="NN1">implicit</w></p>
    <p><w c7="AT">the</w><w c7="NN1">struggle</w><w c7="IO">of</w><w c7="JJ">frightened</w><w c7="JJ">damaged</w><w c7="NN">people</w><w c7="TO">to</w><w c7="VVI">find</w><w c7="NN121">self-</w></p>
    <p><w c7="NN122">expression</w><w c7="CC">and</w><w c7="NN1">fulfilment</w></p>
    <p><w c7="II">in</w><w c7="AT1">a</w><w c7="NN1">society</w></p>
    <p><w c7="DDQGE">whose</w><w c7="JJ">strict</w><w c7="JJ">moral</w><w c7="NN2">codes</w><w c7="VHD">had</w><w c7="RR">always</w><w c7="VVN">inhibited</w><w c7="PPHO2">them</w></p>
    <p><w c7="DD1">that</w><w c7="VBZ">'s</w><w c7="RRQ">why</w></p>
    <p><w c7="AT1">a</w><w c7="NN1">lot</w><w c7="IO">of</w></p>
    <p><w c7="JJ">gay</w><w c7="NN2">writers</w><w c7="VVD">wrote</w><w c7="II">in</w><w c7="AT1">a</w><w c7="NN1">kind</w><w c7="IO">of</w><w c7="NN1">code</w></p>
    <p><w c7="CCB">but</w><w c7="RR">once</w><w c7="DD2">those</w><w c7="JJ">moral</w><w c7="NN2">codes</w><w c7="VVD">began</w><w c7="TO">to</w><w c7="VBI">be</w><w c7="JJ">relaxed</w></p>
    <p><w c7="NP1">Rattigan</w></p>
    <p><w c7="VBDZ">was</w><w c7="XX">not</w><w c7="RR">only</w><w c7="II21">out</w><w c7="II22">of</w><w c7="NN1">fashion</w></p>
    <p><w c7="PPHS1">he</w><w c7="VBDZ">was</w><w c7="JJ">stranded</w></p>
    <p><w c7="XX">not</w><w c7="RR">only</w></p>
    <p><w c7="APPGE">his</w><w c7="NN1">technique</w><w c7="II">as</w><w c7="AT1">a</w><w c7="NN1">writer</w></p>
    <p><w c7="CCB">but</w><w c7="APPGE">his</w><w c7="NN1">background</w><w c7="CC">and</w><w c7="NNT1">lifetime</w><w c7="GE">'s</w><w c7="NN1">conditioning</w></p>
    <p><w c7="VVD">meant</w></p>
    <p><w c7="CST">that</w><w c7="RR">however</w><w c7="RR">passionately</w><w c7="PPHS1">he</w><error><w c7="FU">res-</w></error></p>
    <p><w c7="PPHS1">he</w><w c7="VVD">resented</w><w c7="AT">the</w><w c7="JJ">old</w><w c7="NN2">hypocrisies</w></p>
    <p><w c7="PPHS1">he</w><w c7="VBDZ">was</w><w c7="XX">not</w><w c7="JJ">equipped</w><w c7="TO">to</w><w c7="VVI">make</w><w c7="VDI">do</w><w c7="IW">without</w><w c7="PPHO2">them</w></p>
    <p><w c7="CS">because</w><w c7="PPHS2">they</w></p>
    <p><w c7="VBDR">were</w><w c7="AT">the</w><w c7="NN1">way</w><w c7="PPHS1">he</w><w c7="VVD">made</w><w c7="NN1">art</w></p>
    <p><w c7="AT">the</w><w c7="NN1">result</w><w c7="VBDZ">was</w></p>
    <p><w c7="CST">that</w><w c7="CS">when</w><w c7="PPHS1">he</w><w c7="VVD">tried</w><w c7="TO">to</w><w c7="VVI">confront</w><w c7="NN1">sex</w><w c7="RGQV">however</w><w c7="RR">frankly</w><w c7="CC">and</w><w c7="RR">sincerely</w></p>
    <p><w c7="II">in</w><w c7="AT">the</w><w c7="JJ">permissive</w><w c7="NN1">atmosphere</w></p>
    <p><w c7="IO">of</w><w c7="AT">the</w><w c7="JJ">post-Osborne</w><w c7="NN1">theatre</w></p>
    <p><w c7="PPHS1">he</w><w c7="RR">always</w><w c7="VVD">seemed</w><w c7="JJ">evasive</w></p>
    <p><w c7="JJ">insincere</w></p>
    <p><w c7="CC">and</w><w c7="RT">sometimes</w><w c7="RR">actually</w><w c7="JJ">embarrassing</w></p>
    <p><w c7="PPIS1">I</w><w c7="RT">sometimes</w><w c7="RR">also</w><w c7="VV0">reflect</w><w c7="II">on</w><w c7="DD1">another</w><w c7="NN1">group</w></p>
    <p><w c7="IO">of</w></p>
    <p><w c7="RR">distinctively</w><w c7="JJ">gay</w><w c7="NN2">artists</w><w c7="PNQS">who</w></p>
    <p><w c7="VVD">used</w><w c7="APPGE">their</w></p>
    <p><w c7="NN1">homosexuality</w></p>
    <p><w c7="II">as</w><w c7="AT1">a</w><w c7="NN1">code</w></p>
    <p><w c7="AT1">a</w><w c7="NN1">lot</w><w c7="IO">of</w><w c7="JJ">famous</w><w c7="NN1">radio</w><w c7="NN2">comics</w></p>
    <p><w c7="VVD">spoke</w><w c7="II">to</w><w c7="PPX221">each</w><w c7="PPX222">other</w></p>
    <p><w c7="II">in</w><w c7="AT1">a</w><w c7="NN1">kind</w><w c7="IO">of</w><w c7="NN1">code</w></p>
    <p><w c7="DD1">that</w><w c7="AT1">a</w><w c7="NN1">lot</w><w c7="IO">of</w><w c7="JJ">homophobic</w><w c7="NN">people</w><w c7="VVD">adored</w><w c7="XX">not</w><w c7="VVG">knowing</w></p>
    <p><w c7="DDQ">what</w><w c7="AT">the</w><w c7="NN1">language</w><w c7="VBDZ">was</w><w c7="RR">actually</w><w c7="II">about</w></p>
    <p><w c7="DD1">this</w><w c7="VBZ">is</w></p>
    <p><w c7="NP1">Rebecca</w><w c7="NP1">West</w></p>
    <p><w c7="AT">the</w><w c7="NN1">abnormal</w></p>
    <p><w c7="AT">the</w><w c7="NN1">marginalised</w><w c7="VVG">justifying</w><w c7="PPX2">themselves</w><w c7="VVG">making</w><w c7="NN1">art</w><w c7="II21">out</w><w c7="II22">of</w><w c7="APPGE">their</w><w c7="NN1">pain</w></p>
    <p><w c7="PPIS1">I</w><w c7="VV0">want</w><w c7="TO">to</w><w c7="VVI">conclude</w><w c7="DD1">this</w></p>
    <p><w c7="NN1">section</w><w c7="IO">of</w><w c7="APPGE">my</w><w c7="NN1">thesis</w></p>
    <p><w c7="IW">with</w><w c7="AT1">a</w><w c7="JJ">poignant</w><w c7="NN1">footnote</w><w c7="DD1">that</w><w c7="VVZ">takes</w><w c7="PPIO2">us</w><w c7="RP">back</w><w c7="II">across</w><w c7="AT">the</w><w c7="NP1">Atlantic</w></p>
    <p><w c7="MC1">one</w><w c7="IO">of</w><w c7="AT">the</w><w c7="RGT">most</w><w c7="JJ">remarkable</w><w c7="NN2">illustrations</w><w c7="IO">of</w><w c7="NP1">Rebecca</w><w c7="NP1">West</w><w c7="GE">'s</w><w c7="NN1">claim</w></p>
    <p><w c7="CST">that</w><w c7="JJ">great</w><w c7="NN1">art</w></p>
    <p><w c7="VVZ">comes</w><w c7="II">from</w></p>
    <p><w c7="AT">the</w><w c7="NN2">makers</w><w c7="GE">'</w><w c7="NN1">attempt</w><w c7="TO">to</w><w c7="VVI">bring</w><w c7="NN1">sense</w><w c7="CC">and</w><w c7="NN1">meaning</w><w c7="II21">out</w><w c7="II22">of</w><w c7="NN1">rejection</w><w c7="CC">and</w><w c7="NN1">oppression</w></p>
    <p><w c7="VHZ">has</w><w c7="TO">to</w><w c7="VBI">be</w><w c7="AT">the</w><w c7="NN1">music</w><w c7="DD1">that</w><w c7="VVD">came</w><w c7="II">from</w></p>
    <p><w c7="JJ">African-American</w><w c7="NN2">slaves</w></p>
    <p><w c7="II">in</w><w c7="AT">the</w><w c7="NP121">United</w></p>
    <p><w c7="NP122">States</w></p>
    <p><w c7="VV0">think</w><w c7="IO">of</w><w c7="AT">the</w><w c7="NN1">longing</w></p>
    <p><w c7="CC">and</w><w c7="NN1">pain</w></p>
    <p><w c7="II">in</w><w c7="DD2">those</w><w c7="JJ">famous</w><w c7="NP1">Negro</w><w c7="NN2">spirituals</w></p>
    <p><w c7="CC">and</w><w c7="AT">the</w><w c7="NN1">way</w><w c7="APPGE">their</w><w c7="NN1">music</w></p>
    <p><w c7="VVD">transfigured</w><w c7="NN1">anguish</w><w c7="II">into</w><w c7="NN1">art</w><w c7="PPHS2">they</w><w c7="VV0">make</w><w c7="PPY">you</w><w c7="VVI">cry</w><w c7="AT">the</w><w c7="JJ">very</w><w c7="NN1">thought</w><w c7="IO">of</w><w c7="PPHO2">them</w></p>
    <p><w c7="MC1">one</w><w c7="NN1">way</w><w c7="TO">to</w><w c7="VVI">connect</w></p>
    <p><w c7="IW">with</w><w c7="DD1">that</w><w c7="NN1">tradition</w></p>
    <p><w c7="VBZ">is</w><w c7="II">through</w><w c7="NP1">Michael</w><w c7="NP1">Tippett</w><w c7="GE">'s</w><w c7="NN1">oratorio</w></p>
    <p><w c7="AT1">A</w><w c7="NP1">Child</w><w c7="IO">of</w><w c7="APPGE">Our</w><w c7="NP1">Time</w></p>
    <p><w c7="II">in</w><w c7="DDQ">which</w><w c7="AT">the</w><w c7="JJ">great</w><w c7="NN2">spirituals</w></p>
    <p><w c7="VBR">are</w><w c7="II">like</w><w c7="AT">the</w><w c7="JJ">passionate</w><w c7="NN2">chorals</w><w c7="IO">of</w></p>
    <p><w c7="NP1">Bach</w></p>
    <p><w c7="VVN">used</w><w c7="TO">to</w><w c7="VVI">capture</w><w c7="CC">and</w><w c7="VVI">transcend</w><w c7="JJ">human</w><w c7="NN1">suffering</w></p>
    <p><w c7="PN1">nobody</w><w c7="VVZ">knows</w><w c7="AT">the</w><w c7="NN1">trouble</w><w c7="PPIS1">I</w><w c7="VH0">'ve</w><w c7="VVN">seen</w><w c7="VV0">steal</w><w c7="RL">away</w></p>
    <p><w c7="VV0">steal</w><w c7="RL">away</w></p>
    <p><w c7="VV0">steal</w><w c7="RL">away</w><w c7="II">to</w><w c7="NP1">Jesus</w></p>
    <p><w c7="PPY">you</w><w c7="VM">can</w></p>
    <p><w c7="PPY">you</w><w c7="VM">can</w><w c7="VVI">feel</w><w c7="AT">the</w><w c7="NN1">pain</w><w c7="IO">of</w><w c7="DD2">those</w><w c7="NN">people</w><w c7="VVN">enslaved</w></p>
    <p><w c7="NNO2">thousands</w><w c7="IO">of</w><w c7="NNU2">miles</w><w c7="RL">away</w><w c7="II">from</w><w c7="APPGE">their</w><w c7="DA">own</w><w c7="NN1">homeland</w><w c7="APPGE">their</w><w c7="NN2">hearts</w><w c7="JJ">broken</w></p>
    <p><w c7="VVG">making</w><w c7="NN1">art</w></p>
    <p><w c7="II21">out</w><w c7="II22">of</w><w c7="NN1">torment</w></p>
    <p><w c7="CS">if</w><w c7="PPY">you</w><w c7="VV0">want</w><w c7="DD1">another</w><w c7="NN1">image</w><w c7="TO">to</w></p>
    <p><w c7="VVI">hold</w><w c7="DD1">this</w><w c7="JJ">particular</w><w c7="NN1">enormity</w></p>
    <p><w c7="DD1">that</w></p>
    <p><w c7="VBDZ">was</w><w c7="VVN">transcended</w><w c7="II">into</w><w c7="NN1">beauty</w></p>
    <p><w c7="RT">then</w><w c7="VV0">think</w><w c7="IO">of</w><w c7="AT">the</w><w c7="JJ">great</w><w c7="JJ">persecuted</w><w c7="JJ">African-American</w><w c7="NN1">singer</w></p>
    <p><w c7="NP1">Paul</w><w c7="NP1">Robeson</w></p>
    <p><w c7="PPIS1">I</w><w c7="VH0">have</w><w c7="AT1">an</w><w c7="NN1">image</w><w c7="IO">of</w><w c7="PPHO1">him</w></p>
    <p><w c7="VM">must</w><w c7="VHI">have</w><w c7="VBN">been</w><w c7="II">from</w><w c7="AT1">a</w><w c7="NN1">movie</w></p>
    <p><w c7="VVG">standing</w></p>
    <p><w c7="II">in</w><w c7="AT">the</w><w c7="NN2">chains</w><w c7="IO">of</w><w c7="NN1">slavery</w></p>
    <p><w c7="VVG">singing</w></p>
    <p><w c7="NP1">Ol'</w><w c7="NP1">Man</w><w c7="NNL1">River</w></p>
    <p><w c7="DD1">that</w><w c7="VBZ">'s</w><w c7="AT1">a</w><w c7="JJ">famous</w><w c7="NN1">song</w></p>
    <p><w c7="PPHS1">he</w><w c7="VVD">envied</w><w c7="AT">the</w><w c7="NN1">river</w></p>
    <p><w c7="PPY">you</w><w c7="CC">and</w><w c7="PPIS1">I</w></p>
    <p><w c7="PPHS1">he</w><w c7="VBZ">'s</w><w c7="VVG">singing</w><w c7="II">to</w><w c7="AT">the</w><w c7="JJ">other</w><w c7="NN2">slaves</w><w c7="PPIS2">we</w></p>
    <p><w c7="PPIS2">we</w><w c7="VV0">sweat</w><w c7="CC">and</w><w c7="PPIS2">we</w><w c7="VBR">'re</w><w c7="II">in</w><w c7="NN1">pain</w><w c7="CCB">but</w><w c7="NP1">Ol'</w><w c7="NP1">Man</w><w c7="NNL1">River</w><w c7="PPHS1">he</w><w c7="RR">just</w><w c7="VVZ">keeps</w><w c7="VVG">rolling</w></p>
    <p><w c7="VVG">rolling</w><w c7="RP">on</w></p>
    <p><w c7="CC">and</w><w c7="PPH1">it</w><w c7="VVD">summed</w><w c7="RP">up</w></p>
    <p><w c7="AT">the</w><w c7="NN1">agony</w></p>
    <p><w c7="II">in</w><w c7="DD1">that</w><w c7="NNT1">instant</w><w c7="IO">of</w><w c7="NN1">beauty</w></p>
    <p><w c7="NN1">pain</w><w c7="VVN">transfigured</w><w c7="II">into</w><w c7="JJ">great</w><w c7="NN1">art</w></p>
  </text>
</annotated>