<annotated>
  <text>
    <p><w c7="NP1">Ford</w><w c7="VVZ">breaks</w><w c7="NN1">ankle</w><w c7="II">on</w><w c7="NP121">Star</w><w c7="NP122">Wars</w><w c7="NN1">set</w></p>
    <p><w c7="NP1">Harrison</w><w c7="NP1">Ford</w><w c7="VBZ">is</w><w c7="VBG">being</w><w c7="VVN">treated</w><w c7="II">in</w><w c7="NN1">hospital</w><w c7="II">after</w><w c7="VBG">being</w><w c7="VVN">injured</w><w c7="II">on</w><w c7="AT">the</w><w c7="NN1">set</w><w c7="IO">of</w><w c7="AT">the</w><w c7="JJT">latest</w><w c7="NP121">Star</w><w c7="NP122">Wars</w><w c7="NN1">film</w></p>
    <p><w c7="AT">the</w><w c7="NP1">BBC</w><w c7="VVZ">understands</w><w c7="CST">that</w><w c7="NP1">Ford</w><w c7="MC21">seventy</w><w c7="MC122">one</w></p>
    <p><w c7="VVD">broke</w><w c7="APPGE">his</w><w c7="NN1">ankle</w></p>
    <p><w c7="II">in</w><w c7="AT1">an</w><w c7="NN1">incident</w><w c7="VVG">involving</w></p>
    <p><w c7="AT">the</w><w c7="NN1">door</w><w c7="II">at</w><w c7="NP1">Pinewood</w><w c7="NP2">Studios</w></p>
    <p><w c7="AT">the</w><w c7="NP1">Hollywood</w><w c7="NN1">actor</w></p>
    <p><w c7="PNQS">who</w><w c7="VVD">starred</w><w c7="CSA">as</w><w c7="NP1">Han</w><w c7="NP1">Solo</w></p>
    <p><w c7="II">in</w></p>
    <p><w c7="AT">the</w></p>
    <p><w c7="JJ">original</w><w c7="MC">three</w><w c7="NP121">Star</w><w c7="NP122">Wars</w><w c7="NN2">films</w></p>
    <p><w c7="CC">and</w><w c7="VBZ">is</w><w c7="RR">currently</w><w c7="VVG">filming</w><w c7="AT">the</w><w c7="JJ">new</w><w c7="NP1">Episode</w></p>
    <p><w c7="MC">Seven</w><w c7="NN1">sequel</w></p>
    <p><w c7="VBDZ">was</w><w c7="VVN">airlifted</w><w c7="II">to</w><w c7="NP1">John</w><w c7="NP1">Radcliffe</w><w c7="NP1">Hospital</w><w c7="II">in</w><w c7="NP1">Oxford</w></p>
    <p><w c7="AT1">a</w><w c7="NN1">spokesman</w><w c7="IF">for</w><w c7="NP1">Lucas</w><w c7="NP2">Films</w><w c7="VVD">said</w><w c7="NN1">filming</w><w c7="VM">will</w><w c7="VVI">continue</w></p>
    <p><w c7="CS">while</w><w c7="PPHS1">he</w></p>
	<p><w c7="VV0">recuperate</w></p>
  </text>
</annotated>