<annotated>
  <text>
    <p><w c7="PPIS1">I</w><w c7="VVD">wanted</w><w c7="TO">to</w><w c7="VVI">harden</w><w c7="RP">up</w><w c7="AT">the</w><w c7="NN1">point</w><w c7="RR">so</w></p>
    <p><w c7="PPIS1">I</w><w c7="VV0">think</w><w c7="RG">very</w><w c7="RR">helpfully</w><w c7="NP1">Margaret</w><w c7="VBDZ">was</w><w c7="VVG">making</w></p>
    <p><w c7="CS">because</w></p>
    <p><w c7="RR">even</w><w c7="II">from</w><w c7="APPGE">our</w><w c7="NN1">side</w><w c7="IO">of</w><w c7="AT">the</w></p>
    <p><w c7="AT">the</w><w c7="NN1">fence</w><w c7="RR21">as</w><w c7="RR22">well</w></p>
    <p><w c7="DAT">most</w><w c7="IO">of</w><w c7="PPIO2">us</w><w c7="II">on</w><w c7="DD1">this</w><w c7="NN1">side</w><w c7="IO">of</w><w c7="AT">the</w></p>
    <p><w c7="NN1">horseshoe</w></p>
    <p><w c7="VDD">did</w><w c7="XX">not</w><w c7="VVI">wish</w><w c7="TO">to</w><w c7="VVI">become</w><w c7="JJ">involved</w><w c7="II">in</w><w c7="AT">the</w><w c7="NN1">referendum</w><w c7="NN1">debate</w><w c7="II">on</w><w c7="JJ">partisan</w><w c7="NN2">grounds</w></p>
    <p><w c7="CCB">but</w><w c7="PPIS2">we</w><w c7="VBR">are</w><w c7="RG">very</w><w c7="JJ">keen</w><w c7="TO">to</w><w c7="VHI">have</w><w c7="APPGE">our</w><w c7="APPGE">our</w><w c7="NN1">voice</w><w c7="VVD">heard</w></p>
    <p><w c7="CS21">now</w><w c7="CS22">that</w><w c7="PPIS2">we</w><w c7="VBR">are</w><w c7="RR">actually</w><w c7="JJ">involved</w><w c7="II">in</w></p>
    <p><w c7="II">in</w><w c7="DD1">this</w><w c7="NN1">part</w><w c7="IO">of</w><w c7="AT">the</w><w c7="NN1">discussion</w></p>
    <p><w c7="CC">and</w><w c7="PPIS1">I</w><w c7="VV0">think</w><w c7="PPH1">it</w><w c7="VBZ">'s</w><w c7="JJ">important</w></p>
    <p><w c7="CST">that</w><w c7="DD">some</w><w c7="IO">of</w><w c7="AT">the</w><w c7="RG">very</w><w c7="JJ">welcome</w><w c7="NN2">developments</w><w c7="DD1">that</w><w c7="PPIS2">we</w><w c7="VVD">saw</w><w c7="II">at</w><w c7="DD1">that</w><w c7="NNT1">time</w><w c7="VBDR">were</w><w c7="VVN">continued</w></p>
    <p><w c7="REX21">for</w><w c7="REX22">example</w><w c7="IF">for</w><w c7="AT">the</w><w c7="MD">first</w><w c7="NNT1">time</w></p>
    <p><w c7="AT">the</w><w c7="NN1">treasury</w></p>
    <p><w c7="VVZ">establishes</w><w c7="AT1">an</w><w c7="NN1">office</w></p>
    <p><w c7="II">in</w><w c7="NP1">Scotland</w></p>
    <p><w c7="RR">surprisingly</w><w c7="CS">when</w><w c7="AT">the</w><w c7="NN1">referendum</w><w c7="NN1">campaign</w><w c7="VBZ">'s</w><w c7="VVG">taking</w></p>
    <p><w c7="VVG">taking</w><w c7="NN1">place</w></p>
    <p><w c7="PPIS2">we</w><w c7="VHD">had</w></p>
    <p><w c7="UH">erm</w><w c7="NN1">government</w><w c7="NN2">offices</w></p>
    <p><w c7="UH">erm</w></p>
    <p><w c7="AT1">a</w><w c7="NP1">House</w><w c7="IO">of</w><w c7="NP2">Lords</w><w c7="NN2">committees</w><w c7="RR31">and</w><w c7="RR32">so</w><w c7="RR33">on</w><w c7="VVG">meeting</w><w c7="RP">up</w><w c7="RL">here</w></p>
    <p><w c7="VHD">had</w><w c7="RR">never</w><w c7="VVN">met</w><w c7="RL">here</w><w c7="RT">before</w></p>
    <p><w c7="PPIS2">we</w><w c7="VHD">had</w><w c7="AT1">an</w><w c7="NN1">engagement</w><w c7="RL">there</w><w c7="DD1">that</w><w c7="RL">there</w><w c7="II">from</w><w c7="PPHO2">them</w><w c7="RG">far</w><w c7="RRR">less</w><w c7="II">from</w></p>
    <p><w c7="UH">erm</w><w c7="AT">the</w><w c7="JJ">general</w><w c7="NN1">public</w></p>
    <p><w c7="UH">erm</w><w c7="DD1">that</w><w c7="PPIS2">we</w><w c7="VHD">had</w><w c7="XX">n't</w><w c7="VVN">seen</w><w c7="RT">before</w><w c7="PPIS2">we</w><w c7="VH0">have</w><w c7="TO">to</w><w c7="VVI">retain</w><w c7="DD2">those</w></p>
    <p><w c7="CC">and</w><w c7="PPIS1">I</w><w c7="VV0">think</w><w c7="PPH1">it</w><w c7="VBZ">'s</w><w c7="JJ">important</w></p>
    <p><w c7="CST">that</w></p>
    <p><w c7="II">at</w><w c7="JJ">different</w><w c7="NN2">periods</w><w c7="CS">since</w><w c7="DD1">this</w><w c7="NN1">parliament</w><w c7="VBDZ">was</w><w c7="VVN">established</w></p>
    <p><w c7="UH">erm</w></p>
    <p><w c7="PPIS2">we</w><w c7="VH0">have</w><w c7="VVN">seen</w></p>
    <p><w c7="RR">both</w><w c7="II">at</w><w c7="NNT2">times</w><w c7="RRQ">when</w><w c7="AT">the</w><w c7="DA">same</w><w c7="NN1">party</w><w c7="VBDZ">was</w><w c7="II">in</w><w c7="NN1">command</w></p>
    <p><w c7="II">in</w><w c7="II">in</w><w c7="RR">both</w><w c7="UH">erm</w><w c7="NP1">Whitehall</w><w c7="CC">and</w><w c7="NP1">Holyrood</w></p>
    <p><w c7="CC">and</w><w c7="CS">when</w><w c7="JJ">different</w><w c7="NN2">parties</w><w c7="VBDR">were</w><w c7="RL">there</w></p>
    <p><w c7="AT1">a</w><w c7="NN1">reticence</w><w c7="TO">to</w><w c7="VVI">work</w><w c7="RL">together</w></p>
    <p><w c7="CC">and</w><w c7="UH">erm</w><w c7="PPY">you</w><w c7="VV0">know</w></p>
    <p><w c7="DAR">more</w><w c7="IO">of</w><w c7="AT1">a</w><w c7="AT1">a</w></p>
    <p><error><w c7="FU">a-</w></error></p>
    <p><w c7="AT1">an</w><w c7="NN1">attitude</w></p>
    <p><w c7="IO">of</w></p>
    <p><w c7="RR">almost</w><w c7="VVG">fighting</w><w c7="PPX221">each</w><w c7="PPX222">other</w><w c7="IF">for</w><w c7="NN1">party</w><w c7="NN1">advantage</w></p>
    <p><w c7="CC">and</w><w c7="II">from</w><w c7="APPGE">our</w><w c7="NN1">side</w><w c7="IO">of</w><w c7="AT">the</w><w c7="NN1">fence</w></p>
    <p><w c7="DD1">that</w></p>
    <p><w c7="VBZ">is</w><w c7="JJ">unhelpful</w></p>
    <p><w c7="PPH1">it</w><w c7="VBZ">is</w><w c7="RGT">most</w><w c7="JJ">helpful</w><w c7="II">to</w><w c7="PPIO2">us</w></p>
    <p><w c7="CS">when</w></p>
    <p><w c7="REX21">for</w><w c7="REX22">example</w><w c7="II">in</w><w c7="APPGE">my</w><w c7="NN1">area</w></p>
    <p><w c7="CS">if</w><w c7="NP1">biz</w><w c7="VBR">are</w><w c7="VDG">doing</w><w c7="NN2">things</w></p>
    <p><w c7="DD1">that</w><w c7="VBR">are</w><w c7="JJ">useful</w><w c7="IF">for</w><w c7="AT">the</w><w c7="NN1">promotion</w><w c7="IO">of</w><w c7="JJ">good</w><w c7="NN1">business</w><w c7="NN2">practices</w></p>
    <p><w c7="DD1">that</w><w c7="VM">should</w><w c7="VBI">be</w><w c7="VBG">being</w><w c7="VVN">promoted</w><w c7="II">in</w><w c7="NP1">Scotland</w><w c7="RG">as</w><w c7="RR">much</w><w c7="II">as</w><w c7="RL">anywhere</w><w c7="RR">else</w></p>
    <p><w c7="CC">and</w><w c7="RR">similarly</w></p>
    <p><w c7="CS">if</w><w c7="AT">the</w></p>
    <p><w c7="JJ">Scottish</w><w c7="NN1">government</w><w c7="VBZ">is</w><w c7="VDG">doing</w><w c7="PN1">something</w></p>
    <p><w c7="PPH1">it</w><error><w c7="FU">sh-</w></error></p>
    <p><w c7="PPHS2">they</w><w c7="VM">should</w><w c7="VVI">seek</w><w c7="TO">to</w><w c7="VVI">dovetail</w><w c7="DD1">that</w></p>
    <p><w c7="IW">with</w><w c7="AT">the</w><w c7="NN2">activities</w><w c7="DD1">that</w><w c7="VBR">are</w><w c7="VVG">happening</w><w c7="II">in</w><w c7="AT">the</w><w c7="NP1">UK</w></p>
    <p><w c7="CS">because</w><w c7="DD1">that</w><w c7="VM">will</w><w c7="VBI">be</w><w c7="IF">for</w><w c7="AT">the</w><w c7="NN1">good</w><w c7="IO">of</w><w c7="DB">all</w></p>
    <p><w c7="CS">if</w><w c7="DD1">that</w><w c7="RR">actually</w><w c7="VVZ">takes</w><w c7="NN1">place</w><w c7="CC">and</w><w c7="PPIS1">I</w><w c7="VV0">think</w></p>
    <p><w c7="DD1">that</w></p>
    <p><w c7="PPIS1">I</w></p>
    <p><w c7="PPIS1">I</w><w c7="VV0">suspect</w></p>
    <p><w c7="DD1">that</w></p>
    <p><w c7="NN1">line</w><w c7="DDQ">which</w><w c7="NP1">Margaret</w><w c7="VBDZ">was</w><w c7="VVG">establishing</w><w c7="RL">there</w><w c7="II">about</w><w c7="AT">the</w><w c7="NN1">need</w><w c7="IF">for</w><w c7="DD2">these</w><w c7="MC">two</w><w c7="NN2">governments</w><w c7="TO">to</w><w c7="VVI">work</w><w c7="RL">together</w><w c7="VBZ">is</w><w c7="PN1">one</w><w c7="DD1">that</w><w c7="RR">probably</w><w c7="DB">all</w><w c7="IO">of</w><w c7="PPIO2">us</w><w c7="II">on</w><w c7="DD1">this</w><w c7="NN1">side</w></p>
    <p><w c7="VM">would</w><w c7="VVI">share</w></p>
  </text>
</annotated>